stockobjects/__init__.py
stockobjects/basequote.py
stockobjects/company.py
stockobjects/companycollection.py
stockobjects/companyquote.py
stockobjects/parsing.py
stockobjects/quotecollection.py
stockobjects/sector.py
stockobjects/sectorcollection.py
stockobjects/sectorquote.py
stockobjects/stockobjectsexceptions.py
ctf_stockobjects-0.0.4.dist-info/LICENSE
ctf_stockobjects-0.0.4.dist-info/METADATA
ctf_stockobjects-0.0.4.dist-info/WHEEL
ctf_stockobjects-0.0.4.dist-info/top_level.txt
ctf_stockobjects-0.0.4.dist-info/RECORD
