Metadata-Version: 2.1
Name: ctf-stockobjects
Version: 0.0.4
Summary: A set of basic objects for storing and querying stock market company and sectors
Home-page: https://github.com/chris-t-fernando/stockobjects
Author: Chris Fernando
Author-email: c.fernando@optusnet.com.au
License: UNKNOWN
Project-URL: Bug Tracker, https://github.com/chris-t-fernando/stockobjects/issues
Platform: UNKNOWN
Classifier: Programming Language :: Python :: 3
Classifier: License :: OSI Approved :: MIT License
Classifier: Operating System :: OS Independent
Requires-Python: >=3.6
License-File: LICENSE
